odoo/addons/openupgrade_scripts/README.rst
odoo/addons/openupgrade_scripts/__manifest__.py
odoo/addons/openupgrade_scripts/apriori.py
odoo/addons/openupgrade_scripts/readme/CONFIGURE.rst
odoo/addons/openupgrade_scripts/readme/CONTRIBUTORS.rst
odoo/addons/openupgrade_scripts/readme/DESCRIPTION.rst
odoo/addons/openupgrade_scripts/readme/INSTALL.rst
odoo/addons/openupgrade_scripts/scripts/__dummy__/README.txt
odoo/addons/openupgrade_scripts/scripts/__dummy__/0.0.0.0/pre-.py
odoo/addons/openupgrade_scripts/scripts/account/14.0.1.1/noupdate_changes.xml
odoo/addons/openupgrade_scripts/scripts/account/14.0.1.1/post-migration.py
odoo/addons/openupgrade_scripts/scripts/account/14.0.1.1/pre-migration.py
odoo/addons/openupgrade_scripts/scripts/account/14.0.1.1/upgrade_analysis.txt
odoo/addons/openupgrade_scripts/scripts/account/14.0.1.1/upgrade_analysis_work.txt
odoo/addons/openupgrade_scripts/scripts/account_check_printing/14.0.1.0/noupdate_changes.xml
odoo/addons/openupgrade_scripts/scripts/account_check_printing/14.0.1.0/upgrade_analysis.txt
odoo/addons/openupgrade_scripts/scripts/account_debit_note/14.0.1.0/upgrade_analysis.txt
odoo/addons/openupgrade_scripts/scripts/account_edi/14.0.1.0/upgrade_analysis.txt
odoo/addons/openupgrade_scripts/scripts/account_edi_extended/14.0.1.0/upgrade_analysis.txt
odoo/addons/openupgrade_scripts/scripts/account_edi_facturx/14.0.1.0/upgrade_analysis.txt
odoo/addons/openupgrade_scripts/scripts/account_edi_proxy_client/14.0.1.0/upgrade_analysis.txt
odoo/addons/openupgrade_scripts/scripts/account_edi_ubl/14.0.1.0/upgrade_analysis.txt
odoo/addons/openupgrade_scripts/scripts/account_fleet/14.0.1.0/upgrade_analysis.txt
odoo/addons/openupgrade_scripts/scripts/account_tax_python/14.0.1.0/upgrade_analysis.txt
odoo/addons/openupgrade_scripts/scripts/account_test/14.0.1.0/upgrade_analysis.txt
odoo/addons/openupgrade_scripts/scripts/adyen_platforms/14.0.1.0/upgrade_analysis.txt
odoo14_addon_openupgrade_scripts-14.0.1.0.1.dist-info/METADATA
odoo14_addon_openupgrade_scripts-14.0.1.0.1.dist-info/WHEEL
odoo14_addon_openupgrade_scripts-14.0.1.0.1.dist-info/top_level.txt
odoo14_addon_openupgrade_scripts-14.0.1.0.1.dist-info/RECORD
