Metadata-Version: 2.1
Name: odoo14-addon-openupgrade-scripts
Version: 14.0.1.0.1
Summary: Module that contains all the migrations analysis and scripts for migrate Odoo SA modules.
Home-page: https://github.com/OCA/openupgrade
Author: Odoo Community Association (OCA)
Author-email: support@odoo-community.org
License: AGPL-3
Platform: UNKNOWN
Classifier: Programming Language :: Python
Classifier: Framework :: Odoo
Classifier: Framework :: Odoo :: 14.0
Classifier: License :: OSI Approved :: GNU Affero General Public License v3
Requires-Python: >=3.6
Requires-Dist: odoo (<14.1dev,>=14.0a)
